coco/dev/django_sentry/__init__.py
coco/dev/django_sentry/api.py
coco/dev/django_sentry/apps.py
coco/dev/django_sentry/settings_helpers.py
coco/dev/django_sentry/signals.py
django_sentry_auto_setup-1.0.3.dist-info/licenses/LICENSE.txt
django_sentry_auto_setup-1.0.3.dist-info/METADATA
django_sentry_auto_setup-1.0.3.dist-info/WHEEL
django_sentry_auto_setup-1.0.3.dist-info/top_level.txt
django_sentry_auto_setup-1.0.3.dist-info/RECORD
