Metadata-Version: 2.4
Name: django-sentry-auto-setup
Version: 1.0.3
Summary: Handsfree setup of your Django project inside of Sentry!
Home-page: https://github.com/MrCocoDev/django-sentry-auto-setup
Author: MrCocoDev
Author-email: 3229549+MrCocoDev@users.noreply.github.com
License: MIT
Project-URL: Documentation, https://pyscaffold.org/
Platform: any
Classifier: Development Status :: 4 - Beta
Classifier: Programming Language :: Python
License-File: LICENSE.txt
Requires-Dist: importlib-metadata; python_version < "3.8"
Requires-Dist: httpx
Requires-Dist: sentry-api-python
Requires-Dist: sentry-sdk
Provides-Extra: testing
Requires-Dist: setuptools; extra == "testing"
Requires-Dist: pytest; extra == "testing"
Requires-Dist: pytest-cov; extra == "testing"
Dynamic: license-file
